{"batchcomplete":"","query":{"pages":{"33728":{"pageid":33728,"ns":0,"title":"List of national capitals in alphabetical order","revisions":[{"contentformat":"text/x-wiki","contentmodel":"wikitext","*":"{{Lists of capitals}}\nThis is a '''list of national capitals''' in alphabetical order, including [[Territory (administrative division)|territories]] and [[Dependent territory|dependencies]], non-sovereign states including [[associated state]]s and entities whose [[sovereignty]] is [[Territorial dispute|disputed]]. Sovereign states are shown in bolded text.\n\n{| class=\"wikitable sortable\" style=\"font-size:95%;\"\n!scope=\"col\" style=\"width:120px;\"|City\n!scope=\"col\" style=\"width:200px;\"|Country\n!class=\"sortable\"|Notes\n|-\n| [[Abu Dhabi]]               || '''{{flaglist|United Arab Emirates}}'''||\n|-\n| [[Abuja]]                 ||  '''{{flaglist|Nigeria}}'''|| [[Lagos]] was the capital from 1914 to 1991.\n|-\n| [[Accra]]                   ||  '''{{flaglist|Ghana}}'''||\n|-\n| [[Adamstown, Pitcairn Island|Adamstown]] || {{flaglist|Pitcairn}}|| [[British Overseas Territory]]\n|-\n| [[Addis Ababa]]    ||  '''{{flaglist|Ethiopia}}'''||\n|-\n| [[Algiers]]                 ||  '''{{flaglist|Algeria}}'''||\n|-\n| [[Alofi]]                   || {{flaglist|Niue}}|| Self-governing in [[Associated state|free association]] with [[New Zealand]].\n|-\n| [[Amman]]                   ||  '''{{flaglist|Jordan}}'''||\n|-\n| [[Amsterdam]]               ||  '''{{flaglist|Netherlands}}'''|| The Dutch constitution refers to [[Amsterdam]] as the \"capital\". The Dutch government is located in [[the Hague]]. See [[Capital of the Netherlands]].\n|-\n| [[Andorra la Vella]]        ||  '''{{flaglist|Andorra}}'''||\n|-\n| [[Ankara]]                  ||  '''{{flaglist|Turkey}}'''||\n|-\n| [[Antananarivo]]            ||  '''{{flaglist|Madagascar}}'''||\n|-\n| [[Apia]]                    ||  '''{{flaglist|Samoa}}'''||\n|-\n| [[Ashgabat]]                ||  '''{{flaglist|Turkmenistan}}'''||\n|-\n| [[Asmara]]                  ||  '''{{flaglist|Eritrea}}'''||\n|-\n| [[Astana]]                  ||  '''{{flaglist|Kazakhstan}}'''||\n|-\n| [[Asunci\u00f3n]]                ||  '''{{flaglist|Paraguay}}'''||\n|-\n| [[Athens]]                  ||  '''{{flaglist|Greece}}'''||\n|-\n| [[Avarua]]                  || {{flaglist|Cook Islands}}|| Self-governing in [[Associated state|free association]] with [[New Zealand]].\n|-\n| [[Baghdad]]                 ||  '''{{flaglist|Iraq}}'''||\n|-\n| [[Baku]]                    ||  '''{{flaglist|Azerbaijan}}'''||\n|-\n| [[Bamako]]                  ||  '''{{flaglist|Mali}}'''||\n|-\n| [[Bandar Seri Begawan]]     ||  '''{{flaglist|Brunei}}'''||\n|-\n| [[Bangkok]]                 ||  '''{{flaglist|Thailand}}'''||\n|-\n| [[Bangui]]                  ||  '''{{flaglist|Central African Republic}}'''||\n|-\n| [[Banjul]]                  ||  '''{{flaglist|Gambia}}'''||\n|-\n| [[Basse-Terre]]                 ||  {{flaglist|Guadeloupe}}|| [[Overseas departments and territories of France|Overseas department of France]]\n|-\n| [[Basseterre]]              ||  '''{{flaglist|Saint Kitts and Nevis}}'''||\n|-\n| [[Beijing]]                 ||  '''{{flaglist|China}}'''|| See also: [[List of historical capitals of China]]\n|-\n| [[Beirut]]                  ||  '''{{flaglist|Lebanon}}'''||\n|-\n| [[Belgrade]]                ||  '''{{flaglist|Serbia}}'''||\n|-\n| [[Belmopan]]                ||  '''{{flaglist|Belize}}'''||\n|-\n| [[Berlin]]                  ||  '''{{flaglist|Germany}}'''||\n|-\n| [[Bern]]                    ||  '''{{flaglist|Switzerland}}'''||\n|-\n| [[Bishkek]]                 ||  '''{{flaglist|Kyrgyzstan}}'''||\n|-\n| [[Bissau]]                  ||  '''{{flaglist|Guinea-Bissau}}'''||\n|-\n| [[Bogot\u00e1]]                  ||  '''{{flaglist|Colombia}}'''||\n|-\n| [[Bras\u00edlia]]                ||  '''{{flaglist|Brazil}}'''||\n|-\n| [[Bratislava]]              ||  '''{{flaglist|Slovakia}}'''||\n|-\n| [[Brazzaville]]             ||  '''{{flaglist|Republic of the Congo}}'''||\n|-\n| [[Bridgetown]]              ||  '''{{flaglist|Barbados}}'''||\n|-\n| [[City of Brussels|Brussels]]                ||  '''{{flaglist|Belgium}}'''|| Also the ''de facto'' capital of the {{EU}}\n|-\n| [[Bucharest]]               ||  '''{{flaglist|Romania}}'''||\n|-\n| [[Budapest]]                ||  '''{{flaglist|Hungary}}'''||\n|-\n| [[Buenos Aires]]            ||  '''{{flaglist|Argentina}}'''||\n|-\n| [[Bujumbura]]               ||  '''{{flaglist|Burundi}}'''||\n|-\n| [[Cairo]]                   ||  '''{{flaglist|Egypt}}'''||\n|-\n| [[Canberra]]                ||  '''{{flaglist|Australia}}'''||\n|-\n| [[Caracas]]                 ||  '''{{flaglist|Venezuela}}'''||\n|-\n| [[Castries]]                ||  '''{{flaglist|Saint Lucia}}'''||\n|-\n| [[Cayenne]]                 ||  {{flaglist|French Guiana}}|| [[Overseas departments and territories of France|Overseas department of France]]\n|-\n| [[Charlotte Amalie, United States Virgin Islands|Charlotte Amalie]] || {{flaglist|United States Virgin Islands}}||  [[Territories of the United States|Territory]] of the U.S.\n|-\n| [[Chi\u015fin\u0103u]]                ||  '''{{flaglist|Moldova}}'''||\n|-\n| [[Cockburn Town]]           || {{flaglist|Turks and Caicos Islands}}|| [[British Overseas Territory]]\n|-\n| [[Conakry]]                 ||  '''{{flaglist|Guinea}}'''||\n|-\n| [[Copenhagen]]              ||  '''{{flaglist|Denmark}}'''||\n|-\n| [[Dakar]]                   ||  '''{{flaglist|Senegal}}'''||\n|-\n| [[Damascus]]                ||  '''{{flaglist|Syria}}'''||\n|-\n| [[Dhaka]]                   ||  '''{{flaglist|Bangladesh}}'''||\n|-\n| [[Dili]]                    ||  '''{{flaglist|East Timor|name=East Timor (Timor-Leste)}}'''|| \n|-\n| [[Djibouti (city)|Djibouti]] ||  '''{{flaglist|Djibouti}}'''||\n|-\n| [[Dodoma]] {{small|(official, legislative)}} || '''{{flaglist|Tanzania}}''' || [[Dar es Salaam]], the former capital and largest city continues to serve as the de facto seat of government hosting the [[Ikulu|presidency]], [[Cabinet of Tanzania|government ministries]], [[High Court of Tanzania|judiciary]] and [[List of diplomatic missions in Tanzania|diplomatic missions]]. \n|-\n| [[Doha]]                    ||  '''{{flaglist|Qatar}}'''||\n|-\n| [[Douglas, Isle of Man|Douglas]] || {{flaglist|Isle of Man}}|| British [[Crown Dependency]]\n|-\n| [[Dublin]]                  ||  '''{{flaglist|Ireland}}'''||\n|-\n| [[Dushanbe]]                ||  '''{{flaglist|Tajikistan}}'''||\n|-\n|[[East Jerusalem]] <small>(declared)</small><br>[[Ramallah]] <small>(de facto)</small>|| {{flaglist|Palestinian Authority|name=State of Palestine}} || The State of Palestine claims the territories occupied by Israel since the [[Six-Day War]] in 1967, with [[East Jerusalem]] as its capital. The proclaimed state is currently occupied by Israel and has no effective control over the territories it claims. Administration is based in [[Ramallah]] and [[Gaza City|Gaza]], rather than Jerusalem. Most members of the United Nations regard East Jerusalem as occupied territory, and the [[Organisation of Islamic Cooperation]], the [[Arab League]] and the [[Non-Aligned Movement]] recognise it as the capital of a future Palestinian state.<ref>See the following:\n*{{Cite web|author=Organisation of the Islamic Conference|title=Resolutions on Political, Legal and Information Affairs|work=The Eighteenth Islamic Conference of Foreign Ministers (Session of Islamic Fraternity and Solidarity)|url=http://www.oic-oci.org/english/conf/fm/18/18%20icfm-political-en.htm|date=13\u201316 March 1989|accessdate=2011-10-18}}\n*{{Cite news|author=Agence France-Presse|title=Non-Aligned movement confirms support for Palestinian statehood bid|url=http://english.alarabiya.net/articles/2011/09/06/165700.html|newspaper=Al Arabiya|date=6 September 2011|accessdate=2011-10-18}}\n*{{Citation|author=Council of the European Union|chapter=17218/09 (Presse 371)|title=Press release, 2985th Council meeting on Foreign Affairs|chapter-url=http://www.consilium.europa.eu/uedocs/cms_data/docs/pressdata/EN/foraff/111833.pdf|publisher=Press Office|accessdate=2011-08-02}}</ref> See [[Positions on Jerusalem]].\n|-\n| [[Edinburgh of the Seven Seas]] || {{flaglist|Tristan da Cunha}}|| Part of the [[British Overseas Territory]] of [[Saint Helena, Ascension and Tristan da Cunha]]\n|-\n|  {{nobr|[[Laayoune]] <small>(declared)</small><br>[[Tifariti]] <small>(de facto)</small>}} || {{flaglist|Sahrawi Arab Democratic Republic}}&nbsp;{{Ref label|c|c|none}} || The Sahrawi Republic, recognised by [[Legal status of Western Sahara#States recognizing the SADR|82 states]], claims the mostly [[Morocco|Moroccan]] controlled [[Western Sahara]]. Moroccan controlled territory includes El Aai\u00fan, and Morocco claims all [[Free Zone (region)|Sahrawi controlled territory]]. [[Tifariti]] is factual [[temporary capital]] (instead of [[Bir Lehlou]] earlier) of the SADR. Some government and military structures resides in exile in [[Tindouf]], [[Algeria]].<ref>https://www.cia.gov/library/publications/the-world-factbook/geos/wi.html</ref> See [[Politics of the Sahrawi Arab Democratic Republic]].\n|-\n| [[Episkopi Cantonment]]     || {{flaglist|Akrotiri and Dhekelia}}|| [[British Overseas Territory]]\n|-\n| [[Flying Fish Cove]]  || {{flaglist|Christmas Island}}|| [[States and territories of Australia|External territory]] of [[Australia]]\n|-\n| [[Fort-de-France]]                 ||  {{flaglist|Martinique}}|| [[Overseas departments and territories of France|Overseas department of France]]\n|-\n| [[Freetown]]                ||  '''{{flaglist|Sierra Leone}}'''||\n|-\n| [[Funafuti]]                ||  '''{{flaglist|Tuvalu}}'''||\n|-\n| [[Gaborone]]                ||  '''{{flaglist|Botswana}}'''||\n|-\n| [[George Town, Cayman Islands|George Town]] || {{flaglist|Cayman Islands}}|| [[British Overseas Territory]]\n|-\n| [[Georgetown, Ascension Island|Georgetown]] || {{flaglist|Ascension Island}}|| Part of the [[British Overseas Territory]] of [[Saint Helena, Ascension and Tristan da Cunha]]\n|-\n| [[Georgetown, Guyana|Georgetown]]           ||  '''{{flaglist|Guyana}}'''||\n|-\n| [[Gibraltar]]               || {{flaglist|Gibraltar}}|| [[British Overseas Territory]]\n|-\n| [[Guatemala City]]          ||  '''{{flaglist|Guatemala}}'''||\n|-\n| [[Gustavia, Saint Barth\u00e9lemy|Gustavia]]|| {{flaglist|Saint Barth\u00e9lemy}}|| [[Overseas collectivity]] of [[France]]\n|-\n| [[Hag\u00e5t\u00f1a]]                 || {{flaglist|Guam}}||  [[Territories of the United States|Territory]] of the [[United States]]\n|-\n| [[Hamilton, Bermuda|Hamilton]] || {{flaglist|Bermuda}}|| [[British Overseas Territory]]\n|-\n| [[Hanga Roa]] || {{flaglist|Easter Island}}|| Special territory of [[Chile]]\n|-\n| [[Hanoi]]                   ||  '''{{flaglist|Vietnam}}'''||\n|-\n| [[Harare]]                  ||  '''{{flaglist|Zimbabwe}}'''||\n|-\n| [[Hargeisa]]                || {{flaglist|Somaliland}}||De facto independent state not diplomatically recognized by any other state, claimed in whole by the [[#Somalia|Somali Republic]].<ref>See [http://news.bbc.co.uk/1/hi/world/africa/country_profiles/3794847.stm Regions and territories'': Somaliland] (30 December 2005). BBC News. Retrieved January 17, 2006.</ref>\n|-\n| [[Havana]]                  ||  '''{{flaglist|Cuba}}'''||\n|-\n| [[Helsinki]]                ||  '''{{flaglist|Finland}}'''||\n|-\n| [[Hong Kong]] || {{flaglist|Hong Kong}} || Special administrative region of the People's Republic of China functioning as a [[City-state]],<ref>See http://www.gov.hk/en/about/abouthk/facts.htm (Oktober 2014). Retrieved 4 May 2015.</ref> former British dependent territory.\n|-\n| [[Honiara]]                 ||  '''{{flaglist|Solomon Islands}}'''||\n|-\n| [[Islamabad]]               ||  '''{{flaglist|Pakistan}}'''||\n|-\n| [[Jakarta]]                 ||  '''{{flaglist|Indonesia}}'''||\n|-\n| [[Jamestown, Saint Helena|Jamestown]] || {{flaglist|Saint Helena}}|| Part of the [[British Overseas Territory]] of [[Saint Helena, Ascension and Tristan da Cunha]]\n|-\n| [[Jerusalem]] <small>(declared, de facto)</small> || '''{{flaglist|Israel}}''' || [[Jerusalem Law]] states that \"Jerusalem, complete and united, is the capital of Israel\", and the city serves as the seat of the government, home to the president's residence, government offices, supreme court, and parliament. [[United Nations Security Council Resolution 478]] declared the Jerusalem Law \"null and void\" and called on member states to withdraw their diplomatic missions from Jerusalem. The United Nations and all member states maintain their embassies in other cities such as [[Tel Aviv]], [[Ramat Gan]], and [[Herzliya]], and do not recognise Jerusalem as the capital.<ref>See the [https://www.cia.gov/library/publications/the-world-factbook/geos/is.html CIA Factbook] and [http://www.un.org/Depts/Cartographic/map/profile/israel.pdf Map of Israel]</ref> Many countries officially adhere to the proposal that Jerusalem have international status, as called for in the [[United Nations Partition Plan for Palestine|Partition Plan]] of 1947.<ref>{{cite book |last=Sharkansky |first=Ira |authorlink=Ira Sharkansky |title=Governing Jerusalem: Again on the world's agenda |page=23 |publisher=Wayne State University Press |year=1996 |isbn=0-8143-2592-0}}</ref> The [[Palestinian National Authority]] claims East Jerusalem as the capital of a future Palestinian state. See [[Positions on Jerusalem]].\n|-\n| [[Juba]]                    ||  '''{{flaglist|South Sudan}}'''||\n|-\n| [[Kabul]]                   ||  '''{{flaglist|Afghanistan}}'''||\n|-\n| [[Kampala]]                 ||  '''{{flaglist|Uganda}}'''||\n|-\n| [[Kathmandu]]               ||  '''{{flaglist|Nepal}}'''||\n|-\n| [[Khartoum]]                ||  '''{{flaglist|Sudan}}'''||\n|-\n| [[Kiev]]                    ||  '''{{flaglist|Ukraine}}'''||\n|-\n| [[Kigali]]                  ||  '''{{flaglist|Rwanda}}'''||\n|-\n| [[King Edward Point]]               || {{flaglist|South Georgia and the South Sandwich Islands}}|| [[British Overseas Territory]]\n|-\n| [[Kingston, Jamaica|Kingston]]        ||  '''{{flaglist|Jamaica}}'''||\n|-\n| [[Kingston, Norfolk Island|Kingston]] || {{flaglist|Norfolk Island}}|| [[States and territories of Australia|External territory]] of [[Australia]]\n|-\n| [[Kingstown, Saint Vincent and the Grenadines|Kingstown]] ||  '''{{flaglist|Saint Vincent and the Grenadines}}'''||\n|-\n| [[Kinshasa]]                ||  '''{{flaglist|Democratic Republic of the Congo}}'''||\n|-\n| [[Kuala Lumpur]] <small>(official, legislative and royal)</small><br>[[Putrajaya]] <small>(administrative and judicial)</small> ||  '''{{flaglist|Malaysia}}'''||\n|-\n| [[Kuwait City]]             ||  '''{{flaglist|Kuwait}}'''||\n|-\n| [[Libreville]]              ||  '''{{flaglist|Gabon}}'''||\n|-\n| [[Lilongwe]]                ||  '''{{flaglist|Malawi}}'''||\n|-\n| [[Lima]]                    ||  '''{{flaglist|Peru}}'''|| [[Cusco]] is declared as the \"Historical Capital\" ({{lang-es|''Capital Hist\u00f3rica''}}), a merely symbolic statement, by Article 49 of the [[Peruvian Constitution]].\n|-\n| [[Lisbon]]                  ||  '''{{flaglist|Portugal}}'''||\n|-\n| [[Ljubljana]]               ||  '''{{flaglist|Slovenia}}'''||\n|-\n| [[Lom\u00e9]]                    ||  '''{{flaglist|Togo}}'''||\n|-\n| [[London]]                  ||  '''{{flaglist|United Kingdom}}'''|| Prior to the [[Acts of Union 1707|Acts of Union in 1707]], London was the capital of England only. [[Edinburgh]] was the capital of the [[Kingdom of Scotland]]\n|-\n| [[Luanda]]                  ||  '''{{flaglist|Angola}}'''||\n|-\n| [[Lusaka]]                  ||  '''{{flaglist|Zambia}}'''||\n|-\n| [[Luxembourg (city)|Luxembourg]] ||  '''{{flaglist|Luxembourg}}'''||\n|-\n| [[Madrid]]                  ||  '''{{flaglist|Spain}}'''||\n|-\n| [[Majuro]]                  ||  '''{{flaglist|Marshall Islands}}'''||Self-governing in [[Associated state|free association]] with [[United States]].\n|-\n| [[Malabo]]                  ||  '''{{flaglist|Equatorial Guinea}}'''||\n|-\n| [[Mal\u00e9]]                    ||  '''{{flaglist|Maldives}}'''||\n|-\n| [[Mamoudzou]]                 ||  {{flaglist|Mayotte}}|| [[Overseas departments and territories of France|Overseas department of France]]\n|-\n| [[Managua]]                 ||  '''{{flaglist|Nicaragua}}'''||\n|-\n| [[Manama]]                  ||  '''{{flaglist|Bahrain}}'''||\n|-\n| [[Manila]]                  ||  '''{{flaglist|Philippines}}'''||\n|-\n| [[Maputo]]                  ||  '''{{flaglist|Mozambique}}'''||\n|-\n| [[Marigot, Saint Martin|Marigot]]|| {{flaglist|Saint Martin}}|| [[Overseas collectivity]] of [[France]]\n|-\n| [[Maseru]]                  ||  '''{{flaglist|Lesotho}}'''||\n|-\n| [[Mata-Utu]]                || {{flaglist|Wallis and Futuna}}|| [[Overseas collectivity]] of [[France]]\n|-\n| [[Mbabane]] <small>(administrative)</small><br>[[Lobamba]] <small>(royal and legislative)</small> ||  '''{{flaglist|Swaziland}}'''||\n|-\n| [[Mexico City]]             ||  '''{{flaglist|Mexico}}'''||\n|-\n| [[Minsk]]                   ||  '''{{flaglist|Belarus}}'''||\n|-\n| [[Mogadishu]]               ||  '''{{flaglist|Somalia}}'''||{{anchor|Somalia}}\n|-\n| [[Monaco]]                  ||  '''{{flaglist|Monaco}}'''||[[City-state]]\n|-\n| [[Monrovia]]                ||  '''{{flaglist|Liberia}}'''||\n|-\n| [[Montevideo]]              ||  '''{{flaglist|Uruguay}}'''||\n|-\n| [[Moroni, Comoros|Moroni]]  ||  '''{{flaglist|Comoros}}'''||\n|-\n| [[Moscow]]                  ||  '''{{flaglist|Russia}}'''||\n|-\n| [[Muscat, Oman|Muscat]]     ||  '''{{flaglist|Oman}}'''||\n|-\n| [[Nairobi]]                 ||  '''{{flaglist|Kenya}}'''||\n|-\n| [[Nassau, Bahamas|Nassau]]  ||  '''{{flaglist|Bahamas}}'''||\n|-\n| [[Naypyidaw]]               ||  '''{{flaglist|Myanmar}}'''||\n|-\n| [[N'Djamena]]               ||  '''{{flaglist|Chad}}'''||\n|-\n| [[New Delhi]]               ||  '''{{flaglist|India}}'''||\n|-\n| [[Ngerulmud]]              ||  '''{{flaglist|Palau}}''' ||Self-governing in [[Associated state|free association]] with [[United States]].\n|-\n| [[Niamey]]                  ||  '''{{flaglist|Niger}}'''||\n|-\n| [[Nicosia]]                 ||  '''{{flaglist|Cyprus}}'''||\n|-\n| [[Nicosia]]                 || {{flaglist|Northern Cyprus}}||De facto independent state that is recognised only by [[Turkey]]. Northern Cyprus is claimed in whole by the [[Republic of Cyprus]].<ref>See [https://www.cia.gov/library/publications/the-world-factbook/geos/cy.html The World Factbook|Cyprus] (10 January 2006). Central Intelligence Agency. Retrieved January 17, 2006''.</ref>\n|-\n| [[Nouakchott]]              ||  '''{{flaglist|Mauritania}}'''||\n|-\n| [[Noum\u00e9a]]                  || {{flaglist|New Caledonia}}|| [[Sui generis collectivity]] of [[France]]\n|-\n| [[Nuku\u02bbalofa|Nuku{{Okina}}alofa]] ||  '''{{flaglist|Tonga}}'''||\n|-\n| [[Nuuk]]                    || {{flaglist|Greenland}}|| Self-governing country within the [[Danish Realm|Kingdom of Denmark]]\n|-\n| [[Oranjestad, Aruba|Oranjestad]] || {{flaglist|Aruba}}|| Self-governing country within the [[Kingdom of the Netherlands]]\n|-\n| [[Oslo]]                    ||  '''{{flaglist|Norway}}'''||\n|-\n| [[Ottawa]]                  ||  '''{{flaglist|Canada}}'''||\n|-\n| [[Ouagadougou]]             ||  '''{{flaglist|Burkina Faso}}'''||\n|-\n| [[Pago Pago]]               || {{flaglist|American Samoa}}|| [[Territories of the United States|Territory]] of the [[United States]]\n|-\n| [[Palikir]]                 ||  '''{{flaglist|Federated States of Micronesia}}'''||Self-governing in [[Associated state|free association]] with [[United States]].\n|-\n| [[Panama City]]             ||  '''{{flaglist|Panama}}'''||\n|-\n| [[Papeete]]                 || {{flaglist|French Polynesia}}|| [[Overseas collectivity]] of [[France]]\n|-\n| [[Paramaribo]]              ||  '''{{flaglist|Suriname}}'''||\n|-\n| [[Paris]]                   ||  '''{{flaglist|France}}'''||\n|-\n| [[Philipsburg, Sint Maarten|Philipsburg]] || {{flaglist|Sint Maarten}} || Self-governing country within the [[Kingdom of the Netherlands]]\n|-\n| [[Phnom Penh]]              ||  '''{{flaglist|Cambodia}}'''||\n|-\n| [[Plymouth, Montserrat|Plymouth]] <small>(official)</small><br>[[Brades Estate]] <small>(de facto)</small> || {{flaglist|Montserrat}}|| [[British Overseas Territory]]. Plymouth was abandoned after the eruption of the [[Soufriere Hills volcano]] in 1997. Government offices since then have been moved to [[Brades|Brades Estate]], which is in the northwestern part of Montserrat.\n|-\n| [[Podgorica]] <small>(official)</small><br>[[Cetinje]] <small>(Old Royal Capital, present seat of the [[President of Montenegro|President]])</small> || '''{{flaglist|Montenegro}}'''|| \n|-\n| [[Port Louis]]              ||  '''{{flaglist|Mauritius}}'''||\n|-\n| [[Port Moresby]]            || '''{{flaglist|Papua New Guinea}}'''||\n|-\n| [[Port Vila]]               ||  '''{{flaglist|Vanuatu}}'''||\n|-\n| [[Port-au-Prince]]          ||  '''{{flaglist|Haiti}}'''||\n|-\n| [[Port of Spain]]           ||  '''{{flaglist|Trinidad and Tobago}}'''||\n|-\n| [[Porto-Novo]] <small>(official)</small><br>[[Cotonou]] <small>(de facto)</small>             ||  '''{{flaglist|Benin}}''' ||\n|-\n| [[Prague]]                  ||  '''{{flaglist|Czech Republic}}'''||\n|-\n| [[Praia]]                   ||  '''{{flaglist|Cabo Verde}}'''||\n|-\n| [[Pretoria]] <small>(executive)</small><br>[[Bloemfontein]] <small>(judicial)</small><br>[[Cape Town]] <small>(legislative)</small>               ||  '''{{flaglist|South Africa}}'''||\n|-\n| [[Pristina]]                || {{flaglist|Kosovo}}{{Ref label|g|g|none}}||De facto independent state that is recognised by {{Numrec|Kos}} UN member states and by [[Taiwan]]. Claimed in whole by the Republic of Serbia as part of its [[Kosovo|Autonomous Province of Kosovo and Metohija]]. Republic of Kosovo has ''[[de facto]]'' control over most of the territory, with limited control in [[North Kosovo]]. \n|-\n| [[Pyongyang]]               ||  '''{{flaglist|North Korea}}'''||\n|-\n| [[Quito]]                   ||  '''{{flaglist|Ecuador}}'''|| Highest official capital (2,850 m).<ref name = \"Highest\">{{cite web|url=http://opinionator.blogs.nytimes.com/2012/06/19/amazonia-or-bust/#ftn3 |title=Amazonia or Bust! |last=Jacobs |first=Frank |publisher=New York Times |date=19 June 2012 |accessdate=28 June 2012}}</ref>\n|-\n| [[Rabat]]                   ||  '''{{flaglist|Morocco}}'''||\n|-\n| [[Reykjav\u00edk]]               ||  '''{{flaglist|Iceland}}'''||\n|-\n| [[Riga]]                    ||  '''{{flaglist|Latvia}}'''||\n|-\n| [[Riyadh]]                  || '''{{flaglist|Saudi Arabia}}'''||\n|-\n| [[Road Town]]               || {{flaglist|British Virgin Islands}}|| [[British Overseas Territory]]\n|-\n| [[Rome]]                    ||  '''{{flaglist|Italy}}'''||\n|-\n| [[Roseau]] ||  '''{{flaglist|Dominica}}'''||\n|-\n| [[Saint-Denis, R\u00e9union|Saint-Denis]]                 ||  {{flaglist|R\u00e9union}}|| [[Overseas departments and territories of France|Overseas department of France]]\n|-\n| [[Saipan]]                  || {{flaglist|Northern Mariana Islands}}||  [[Territories of the United States|Territory]] of the [[United States]]\n|-\n| [[San Jos\u00e9, Costa Rica|San Jos\u00e9]]     ||  '''{{flaglist|Costa Rica}}'''||\n|-\n| [[San Juan, Puerto Rico|San Juan]]    || {{flaglist|Puerto Rico}}|| [[Territories of the United States|Territory]] of the [[United States]]\n|-\n| [[City of San Marino|San Marino]] ||  '''{{flaglist|San Marino}}'''||\n|-\n| [[San Salvador]]             ||  '''{{flaglist|El Salvador}}'''||\n|-\n| [[Sana'a]]                    ||  '''{{flaglist|Yemen}}'''||\n|-\n| [[Santiago]] ||  '''{{flaglist|Chile}}'''||The [[National Congress of Chile]] is located in [[Valpara\u00edso]]\n|-\n| [[Santo Domingo]]            ||  '''{{flaglist|Dominican Republic}}'''||\n|-\n| [[S\u00e3o Tom\u00e9]]                 ||  '''{{flaglist|Sao Tome and Principe}}'''||\n|-\n| [[Sarajevo]]                 ||  '''{{flaglist|Bosnia and Herzegovina}}'''||\n|-\n| [[Seoul]]                    ||  '''{{flaglist|South Korea}}'''||\n|-\n| [[Singapore]]                ||  '''{{flaglist|Singapore}}'''||[[City-state]]\n|-\n| [[Skopje]]                   ||  '''{{flaglist|Republic of Macedonia}}'''||\n|-\n| [[Sofia]]                    ||  '''{{flaglist|Bulgaria}}'''||\n|-\n| [[Sri Jayawardenepura Kotte]] <small>(official)</small><br>[[Colombo]] <small>(former capital; has some government offices)</small> ||  '''{{flaglist|Sri Lanka}}''' || Also known as \"Kotte\". Until the 1980s, the capital was [[Colombo]], where many important governmental institutions still remain and which is still designated as the commercial capital of Sri Lanka.\n|-\n| [[St. George's, Grenada|St. George's]] ||  '''{{flaglist|Grenada}}'''||\n|-\n| [[St. Helier]]               || {{flaglist|Jersey}}|| British [[Crown Dependency]]\n|-\n| [[St. John's, Antigua and Barbuda|St. John's]]       ||  '''{{flaglist|Antigua and Barbuda}}'''||\n|-\n| [[St. Peter Port]]           ||  {{flaglist|Guernsey}}|| British [[Crown Dependency]]\n|-\n| [[St. Pierre, Saint-Pierre and Miquelon|St. Pierre]] || {{flaglist|Saint Pierre and Miquelon}}|| [[Overseas collectivity]] of [[France]]\n|-\n| [[Stanley, Falkland Islands|Stanley]]  || {{flaglist|Falkland Islands}}|| [[British Overseas Territory]]\n|-\n| [[Stepanakert]]                        ||  {{flaglist|Nagorno-Karabakh Republic}}|| The self-declared country remains diplomatically unrecognised by UN-member states, including Armenia. Transnistria, South Ossetia, and Abkhazia, all UN non-member states, recognise the state. Claimed in whole by Azerbaijan.\n|-\n| [[Stockholm]]                ||  '''{{flaglist|Sweden}}'''||\n|-\n| [[Sucre]] <small>(constitutional)</small><br>[[La Paz]] <small>(administrative)</small> ||  '''{{flaglist|Bolivia}}'''|| [[La Paz]] is the highest administrative capital (3,650 m), higher than Quito.<ref name=\"Highest\"/>\n|-\n| [[Sukhumi]]                    ||  {{flaglist|Abkhazia}}|| De facto independent state recognised by Russia, Nauru, Nicaragua, Venezuela, South Ossetia and Transnistria. Claimed in whole by [[Georgia (country)|Republic of Georgia]] as the [[Autonomous Republic of Abkhazia]].\n|-\n| [[Suva]]                     ||  '''{{flaglist|Fiji}}'''||\n|-\n| [[Taipei]]                ||  '''{{flaglist|Taiwan}}''' || Officially the Republic of China (ROC), it has been competing for recognition with the [[China|People's Republic of China]] (PRC) as the sole Chinese government since 1949. Taiwan controls the island of Taiwan and its associated islands, Quemoy, Matsu, the Pratas, and part of the [[Spratly Islands]]<ref name=\"Spratly\" group=Note>The sovereignty over the [[Spratly Islands]] is disputed by the PRC, the ROC, [[Vietnam]], the [[Philippines]] (part), [[Malaysia]] (part), and [[Brunei]] (part). Except Brunei, each of these countries occupies part of the islands (see [[List of territorial disputes]]).</ref> The territory of Taiwan is claimed in whole by the People's Republic of China.<ref name=\"TAI2\" group=Note>In 1949, the Republic of China government led by the [[Kuomintang]] (KMT) lost the [[Chinese Civil War]] to the [[Communist Party of China]] (CPC) and set up a provisional capital in Taipei. The CPC established the People's Republic. As such, the [[Political status of Taiwan|political status]] of the ROC and the [[legal status of Taiwan]] (alongside the [[Free Area of the Republic of China|territories]] currently under ROC jurisdiction) are in dispute. In 1971, the [[United Nations]] gave the [[China and the United Nations|China seat]] to the PRC instead of the ROC: most states recognize the PRC to be the [[One-China policy|sole legitimate representative of all China]], and the UN classifies Taiwan as \"[[Taiwan Province, People's Republic of China|Taiwan, Province of China]]\". The ROC has ''de facto'' relations with most sovereign states. A significant political movement within Taiwan advocates [[Taiwan independence]].</ref> The Republic of China participates in the [[World Health Organization]] and a number of non-UN international organizations such as the [[World Trade Organization]], [[International Olympic Committee]] and others under a variety of pseudonyms, most commonly [[Chinese Taipei]].\n|-\n| [[Tallinn]]                  ||  '''{{flaglist|Estonia}}'''||\n|-\n\n| [[Tarawa Atoll]]                   ||  '''{{flaglist|Kiribati}}'''||\n|-\n| [[Tashkent]]                 ||  '''{{flaglist|Uzbekistan}}'''||\n|-\n| [[Tbilisi]] <small>(official)</small><br>[[Kutaisi]] <small>(legislative)</small>  ||  '''{{flaglist|Georgia}}'''||\n|-\n| [[Tegucigalpa]]              ||  '''{{flaglist|Honduras}}'''||\n|-\n| [[Tehran]]                   ||  '''{{flaglist|Iran}}'''||\n|-  \n| [[Thimphu]]                  ||  '''{{flaglist|Bhutan}}'''||\n|-\n| [[Tirana]]                   ||  '''{{flaglist|Albania}}'''||\n|-\n| [[Tiraspol]]                 || {{flaglist|Transnistria}}|| De facto independent state, not recognized by any UN-member, but by Abkhazia and South Ossetia. Claimed in whole by the [[Republic of Moldova]] as the ''Territorial Unit of Transnistria''.\n|-\n| [[Tokyo]]                    ||  '''{{flaglist|Japan}}'''||\n|-\n| [[T\u00f3rshavn]]                 || {{flaglist|Faroe Islands}}|| Self-governing country within the [[Danish Realm|Kingdom of Denmark]]\n|-\n| [[Tripoli]]                  ||  '''{{flaglist|Libya}}'''||\n|-\n| [[Tskhinvali]]               || {{flaglist|South Ossetia}}|| De facto independent state recognised by Russia, Nicaragua, Nauru, Venezuela, Abkhazia and Transnistria. Claimed in whole by the [[Georgia (country)|Republic of Georgia]] as the [[Provisional Administrative Entity of South Ossetia]].\n|-\n| [[Tunis]]                    ||  '''{{flaglist|Tunisia}}'''||\n|-\n| [[Ulaanbaatar]]              ||  '''{{flaglist|Mongolia}}'''||\n|-\n| [[Vaduz]]                    ||  '''{{flaglist|Liechtenstein}}'''||\n|-\n| [[Valletta]]                 ||  '''{{flaglist|Malta}}'''||\n|-\n| [[The Valley, Anguilla|The Valley]] || {{flaglist|Anguilla}}|| [[British Overseas Territory]]\n|-\n| [[Vatican City]]             ||  '''{{flaglist|Vatican City}}'''||[[City-state]]\n|-\n| [[Victoria, Seychelles|Victoria]]   ||  '''{{flaglist|Seychelles}}'''||\n|-\n| [[Vienna]]                   ||  '''{{flaglist|Austria}}'''||\n|-\n| [[Vientiane]]                ||  '''{{flaglist|Laos}}'''||\n|-\n| [[Vilnius]]                  ||  '''{{flaglist|Lithuania}}'''||\n|-\n| [[Warsaw]]                   ||  '''{{flaglist|Poland}}'''||\n|-\n| [[Washington, D.C.]]         ||  '''{{flaglist|United States}}'''||\n|-\n| [[Wellington]]               ||  '''{{flaglist|New Zealand}}'''||\n|-\n| [[West Island, Cocos (Keeling) Islands|West Island]] || {{flaglist|Cocos (Keeling) Islands}}|| [[States and territories of Australia|External territory]] of [[Australia]]\n|-\n| [[Willemstad]]      || {{flaglist|Cura\u00e7ao}}|| Self-governing country within the [[Kingdom of the Netherlands]]\n|-\n| [[Windhoek]]                 ||  '''{{flaglist|Namibia}}'''||\n|-\n| [[Yamoussoukro]] <small>(official)</small><br>[[Abidjan]] <small>(former capital; still has many government offices)</small>             ||  '''{{flaglist|C\u00f4te d'Ivoire}}'''||\n|-\n| [[Yaound\u00e9]]                  ||  '''{{flaglist|Cameroon}}'''||\n|-\n| [[Yaren district|Yaren]] <small>(de facto)</small>     ||  '''{{flaglist|Nauru}}''' ||Country does not have an official capital; however, the government offices are in Yaren.\n|-\n| [[Yerevan]]                  ||  '''{{flaglist|Armenia}}'''||\n|-\n| [[Zagreb]]                   ||  '''{{flaglist|Croatia}}'''||\n|}"}]}}}}